sssom_schema/__init__.py
sssom_schema/context/sssom_schema.context.jsonld
sssom_schema/context/sssom_schema.jsonld
sssom_schema/datamodel/__init__.py
sssom_schema/datamodel/sssom_schema.py
sssom_schema/schema/sssom_schema.yaml
sssom_schema-1.0.0.dist-info/LICENSE
sssom_schema-1.0.0.dist-info/METADATA
sssom_schema-1.0.0.dist-info/WHEEL
sssom_schema-1.0.0.dist-info/RECORD
