Metadata-Version: 2.1
Name: sssom-schema
Version: 1.0.0
Summary: SSSOM is a Simple Standard for Sharing Ontology Mappings.
License: MIT
Author: Nicolas Matentzoglu
Author-email: nicolas.matentzoglu@gmail.com
Requires-Python: >=3.8.1,<4.0.0
Classifier: License :: OSI Approved :: MIT License
Classifier: Programming Language :: Python :: 3
Classifier: Programming Language :: Python :: 3.9
Classifier: Programming Language :: Python :: 3.10
Classifier: Programming Language :: Python :: 3.11
Classifier: Programming Language :: Python :: 3.12
Provides-Extra: docs
Requires-Dist: linkml-runtime
